debug_helper/__init__.py
debug_helper/cli.py
debug_helper/client.py
debug_helper/sdk.py
debug_helper/utils.py
debug_helper-1.0.0.dist-info/licenses/LICENSE
debug_helper-1.0.0.dist-info/METADATA
debug_helper-1.0.0.dist-info/WHEEL
debug_helper-1.0.0.dist-info/entry_points.txt
debug_helper-1.0.0.dist-info/top_level.txt
debug_helper-1.0.0.dist-info/RECORD
